tests/__init__.py
tests/test_tuttusa_proxy.py
tuttusa_proxy/__init__.py
tuttusa_proxy/cli.py
tuttusa_proxy/tuttusa_proxy.py
tuttusa_proxy-0.1.dist-info/AUTHORS.md
tuttusa_proxy-0.1.dist-info/LICENSE
tuttusa_proxy-0.1.dist-info/METADATA
tuttusa_proxy-0.1.dist-info/WHEEL
tuttusa_proxy-0.1.dist-info/top_level.txt
tuttusa_proxy-0.1.dist-info/RECORD
